kubernetes_mcp_server/__init__.py
kubernetes_mcp_server/__main__.py
kubernetes_mcp_server/kubernetes_mcp_server.py
kiali_mcp_server-0.5.0.dist-info/METADATA
kiali_mcp_server-0.5.0.dist-info/WHEEL
kiali_mcp_server-0.5.0.dist-info/entry_points.txt
kiali_mcp_server-0.5.0.dist-info/top_level.txt
kiali_mcp_server-0.5.0.dist-info/RECORD
