Metadata-Version: 2.4
Name: kiali-mcp-server
Version: 0.5.0
Summary: Kiali MCP Server (Model Context Protocol) with special support for OpenShift
Author-email: Marc Nuri <marc@marcnuri.com>
License-Expression: Apache-2.0
Project-URL: Homepage, https://github.com/kiali/kiali-mcp-server
Project-URL: Repository, https://github.com/kiali/kiali-mcp-server
Classifier: Programming Language :: Python :: 3
Classifier: Operating System :: OS Independent
Requires-Python: >=3.6
